CiliaTracks/__init__.py
CiliaTracks/constants.py
CiliaTracks/converter.py
CiliaTracks/displacement.py
CiliaTracks/model.py
CiliaTracks/prediction_CNN.py
CiliaTracks/prediction_ML.py
CiliaTracks/speed.py
CiliaTracks/track_ML.py
CiliaTracks/trajectory.py
CiliaTracks/trajectory_CNN.py
CiliaTracks/utils.py
CiliaTracks/models/__init__.py
CiliaTracks/models/trajectory_cnn_model.pth
CiliaTracks/models/tuned_xgboost_model.joblib
ciliatracks-1.1.2.dist-info/licenses/LICENSE
ciliatracks-1.1.2.dist-info/METADATA
ciliatracks-1.1.2.dist-info/WHEEL
ciliatracks-1.1.2.dist-info/top_level.txt
ciliatracks-1.1.2.dist-info/RECORD
