Metadata-Version: 2.4
Name: CiliaTracks
Version: 1.1.2
Summary: A package for analyzing cilia-driven particle motility from TrackMate data.
Author-email: Nicholas Hadas <hadasn@wustl.edu>
License-Expression: GPL-3.0-or-later
Project-URL: Homepage, https://github.com/NicoHadas/CiliaTracks
Project-URL: Issues, https://github.com/NicoHadas/CiliaTracks/issues
Classifier: Programming Language :: Python :: 3
Classifier: Operating System :: OS Independent
Requires-Python: >=3.8
License-File: LICENSE
Requires-Dist: pandas
Requires-Dist: numpy
Requires-Dist: matplotlib
Requires-Dist: joblib
Requires-Dist: xgboost
Requires-Dist: torch
Requires-Dist: torchvision
Requires-Dist: Pillow
Dynamic: license-file
